{
   "factual_sample": {
      "seismic": 0,
      "seismoacoustic": 0,
      "shift": 0,
      "genergy": 5890,
      "gpuls": 301,
      "gdenergy": -43,
      "gdpuls": -13,
      "ghazard": 0,
      "nbumps": 0,
      "nbumps2": 0,
      "nbumps3": 0,
      "nbumps4": 0,
      "nbumps5": 0,
      "energy": 0,
      "maxenergy": 0,
      "y": false
   },
   "counterfactual_sample": {
      "seismic": 0,
      "seismoacoustic": 0,
      "shift": 0,
      "genergy": 6031,
      "gpuls": 194,
      "gdenergy": -43,
      "gdpuls": 0,
      "ghazard": 0,
      "nbumps": 0,
      "nbumps2": 0,
      "nbumps3": 0,
      "nbumps4": 0,
      "nbumps5": 0,
      "energy": 40,
      "maxenergy": 26,
      "y": true
   },
   "counterfactual_found": true,
   "counterfactual_plausible": true,
   "counterfactual_distance": 0.002522065992351322,
   "counterfactual_time": 7.9390294551849365,
   "counterfactual_class": 1,
   "factual_class": 0,
   "valid_": true
}