{
   "factual_sample": {
      "Temperature": -0.3637525876470167,
      "Humidity": 0.4342758479273515,
      "Light": -0.7724036570242273,
      "CO2": -0.24367716780342416,
      "HumidityRatio": 0.07792587591847218,
      "y": 1
   },
   "counterfactual_sample": {
      "Temperature": -0.2275434623222056,
      "Humidity": 0.3296712252619181,
      "Light": 0.994437595600923,
      "CO2": 0.4075504912858314,
      "HumidityRatio": 0.07054514216764639,
      "y": 0
   },
   "counterfactual_found": true,
   "counterfactual_plausible": true,
   "counterfactual_distance": 0.10371113980177352,
   "counterfactual_time": 0.19258737564086914,
   "counterfactual_class": 0,
   "factual_class": 1,
   "valid_": true
}