{
   "counterfactual_sample": {
      "EducationLevel": 4.0, 
      "MaritalStatus": 0.0, 
      "WorkClass": 2.0, 
      "Relationship": 4.0, 
      "age": 39.0, 
      "EducationNumber": 10.0, 
      "y": 0, 
      "HoursPerWeek": 40.0, 
      "NativeCountry": 0.0, 
      "CapitalGain": 0.057473, 
      "CapitalLoss": 1.3128994042227844, 
      "Occupation": 3.0
   }, 
   "factual_class": 0, 
   "factual_sample": {
      "EducationLevel": 4.0, 
      "MaritalStatus": 0.0, 
      "WorkClass": 2.0, 
      "Relationship": 4.0, 
      "age": 39.0, 
      "CapitalLoss": 1.3128994042227844, 
      "y": 0, 
      "HoursPerWeek": 40.0, 
      "NativeCountry": 0.0, 
      "CapitalGain": -0.1473664551602441, 
      "EducationNumber": 10.0, 
      "Occupation": 3.0
   }, 
   "counterfactual_distance": 0.0013532433964616624, 
   "counterfactual_class": 0, 
   "counterfactual_rule": {
      "CapitalGain": ">0.056473"
   }, 
   "counterfactual_time": 16.23935103416443, 
   "counterfactual_found": false
}