{
   "counterfactual_sample": {
      "genergy": 101040, 
      "seismoacoustic": 0, 
      "ghazard": 0, 
      "shift": 1, 
      "energy": 1700, 
      "maxenergy": 1000, 
      "gdenergy": -82.0, 
      "gpuls": 531.0, 
      "nbumps4": 0, 
      "y": 0, 
      "nbumps5": 0, 
      "seismic": 0, 
      "nbumps": 2, 
      "gdpuls": 11, 
      "nbumps2": 1, 
      "nbumps3": 1
   }, 
   "factual_class": 0, 
   "factual_sample": {
      "genergy": 101040, 
      "maxenergy": 1000, 
      "y": 0, 
      "shift": 1, 
      "energy": 1700, 
      "seismoacoustic": 0, 
      "gdenergy": 11, 
      "gpuls": 213, 
      "nbumps4": 0, 
      "ghazard": 0, 
      "nbumps5": 0, 
      "seismic": 0, 
      "nbumps3": 1, 
      "gdpuls": 11, 
      "nbumps2": 1, 
      "nbumps": 2
   }, 
   "counterfactual_distance": 0.009317835202237269, 
   "counterfactual_class": 0, 
   "counterfactual_rule": {
      "gpuls": ">530.0", 
      "gdenergy": "<=-82.0"
   }, 
   "counterfactual_time": 14.099892139434814, 
   "counterfactual_found": false
}