{
   "counterfactual_sample": {
      "density": 3, 
      "age": 51.0, 
      "shape": 4, 
      "bi-rads": 4, 
      "y": 1, 
      "margin": 4
   }, 
   "factual_class": 0, 
   "factual_sample": {
      "density": 3, 
      "age": 52, 
      "shape": 4, 
      "bi-rads": 4, 
      "y": 0, 
      "margin": 4
   }, 
   "counterfactual_distance": 0.002564102564102564, 
   "counterfactual_class": 1, 
   "counterfactual_rule": {
      "age": "49.218965< age <=51.340924", 
      "bi-rads": "<=4.482484"
   }, 
   "counterfactual_time": 10.505719900131226, 
   "counterfactual_found": true
}