{
   "counterfactual_sample": {
      "isMale": 0.0, 
      "EducationLevel": 3.0, 
      "MostRecentBillAmount": -0.6012513133287795, 
      "MonthsWithLowSpendingOverLast6Months": 6.0, 
      "MaxPaymentAmountOverLast6Months": -0.02722790960068537, 
      "isMarried": 1.0, 
      "MaxBillAmountOverLast6Months": -0.737963, 
      "TotalOverdueCounts": 0.0, 
      "MonthsWithZeroBalanceOverLast6Months": 4.0, 
      "HasHistoryOfOverduePayments": 0.0, 
      "y": 0, 
      "TotalMonthsOverdue": 1.0, 
      "MostRecentPaymentAmount": -0.35263009297023656, 
      "AgeGroup": 2.0, 
      "MonthsWithHighSpendingOverLast6Months": 0.0
   }, 
   "factual_class": 1, 
   "factual_sample": {
      "isMale": 0.0, 
      "EducationLevel": 3.0, 
      "MostRecentBillAmount": -0.6012513133287795, 
      "MaxPaymentAmountOverLast6Months": -0.02722790960068537, 
      "HasHistoryOfOverduePayments": 0.0, 
      "isMarried": 1.0, 
      "MaxBillAmountOverLast6Months": -0.6838163912115257, 
      "MostRecentPaymentAmount": -0.35263009297023656, 
      "y": 1, 
      "MonthsWithZeroBalanceOverLast6Months": 4.0, 
      "TotalMonthsOverdue": 0.0, 
      "TotalOverdueCounts": 0.0, 
      "MonthsWithLowSpendingOverLast6Months": 6.0, 
      "AgeGroup": 2.0, 
      "MonthsWithHighSpendingOverLast6Months": 0.0
   }, 
   "counterfactual_distance": 0.002293240097505669, 
   "counterfactual_class": 0, 
   "counterfactual_rule": {
      "isMale": "<=0.184721", 
      "TotalMonthsOverdue": "0.191864< TotalMonthsOverdue <=3.658973", 
      "MaxBillAmountOverLast6Months": "<=-0.737963"
   }, 
   "counterfactual_time": 19.442015886306763, 
   "counterfactual_found": true
}