{
   "factual_sample": {
      "variance_wti": -0.2794481747453968,
      "skewness_wti": 0.3738676438485409,
      "curtosis_wty": 0.3984424235278459,
      "entropy": 0.3902714272183633
   },
   "counterfactual_sample": {
      "variance_wti": -0.25640999999999997,
      "skewness_wti": 0.48344,
      "curtosis_wty": 0.3984424235278459,
      "entropy": 0.3902714272183633
   },
   "factual_class": 1,
   "counterfactual_class": 0,
   "counterfactual_found": true,
   "counterfactual_rule_id": 96,
   "counterfactual_rule": {
      "0": [
         -0.26141,
         -0.23858
      ],
      "1": [
         0.47844,
         0.51388
      ],
      "2": [
         0.32954,
         1.09541
      ],
      "3": [
         0.37673,
         1.09461
      ]
   },
   "counterfactual_distance": 0.007193935842411429,
   "counterfactual_time": 1.10789155960083
}