{
   "counterfactual_sample": {
      "isMale": 0.0, 
      "EducationLevel": 3.0, 
      "MostRecentBillAmount": -0.5040058738506862, 
      "MonthsWithLowSpendingOverLast6Months": 1.0, 
      "MaxPaymentAmountOverLast6Months": 5.922614323724685, 
      "isMarried": 0.0, 
      "MaxBillAmountOverLast6Months": 2.0568221580244166, 
      "TotalOverdueCounts": 1.0, 
      "MonthsWithZeroBalanceOverLast6Months": 1.0, 
      "HasHistoryOfOverduePayments": 1.0, 
      "y": 0, 
      "TotalMonthsOverdue": 2.0, 
      "MostRecentPaymentAmount": 15.31431872398778, 
      "AgeGroup": 2.0, 
      "MonthsWithHighSpendingOverLast6Months": 2.0
   }, 
   "factual_class": 0, 
   "factual_sample": {
      "isMale": 0.0, 
      "EducationLevel": 3.0, 
      "MostRecentBillAmount": -0.5040058738506862, 
      "MaxPaymentAmountOverLast6Months": 5.922614323724685, 
      "HasHistoryOfOverduePayments": 1.0, 
      "isMarried": 0.0, 
      "MaxBillAmountOverLast6Months": 2.0568221580244166, 
      "MostRecentPaymentAmount": 15.31431872398778, 
      "y": 0, 
      "MonthsWithZeroBalanceOverLast6Months": 1.0, 
      "TotalMonthsOverdue": 2.0, 
      "TotalOverdueCounts": 1.0, 
      "MonthsWithLowSpendingOverLast6Months": 1.0, 
      "AgeGroup": 2.0, 
      "MonthsWithHighSpendingOverLast6Months": 2.0
   }, 
   "counterfactual_distance": 0.0, 
   "counterfactual_class": 0, 
   "counterfactual_rule": {
      "TotalOverdueCounts": "0.266591< TotalOverdueCounts <=1.150056", 
      "isMale": "<=0.372519"
   }, 
   "counterfactual_time": 18.739935874938965, 
   "counterfactual_found": false
}