{
   "factual_sample": {
      "isMale": 0.0,
      "isMarried": 1.0,
      "AgeGroup": 1.0,
      "EducationLevel": 3.0,
      "MaxBillAmountOverLast6Months": -0.30062680681987425,
      "MaxPaymentAmountOverLast6Months": -0.3403775008283364,
      "MonthsWithZeroBalanceOverLast6Months": 0.0,
      "MonthsWithLowSpendingOverLast6Months": 0.0,
      "MonthsWithHighSpendingOverLast6Months": 6.0,
      "MostRecentBillAmount": -0.2432112861594361,
      "MostRecentPaymentAmount": -0.3747273409490208,
      "TotalOverdueCounts": 1.0,
      "TotalMonthsOverdue": 12.0,
      "HasHistoryOfOverduePayments": 1.0,
      "y": true
   },
   "counterfactual_sample": {
      "isMale": 0,
      "isMarried": 1,
      "AgeGroup": 1,
      "EducationLevel": 3,
      "MaxBillAmountOverLast6Months": -0.300764196982509,
      "MaxPaymentAmountOverLast6Months": -0.36274532973766327,
      "MonthsWithZeroBalanceOverLast6Months": 0,
      "MonthsWithLowSpendingOverLast6Months": 0,
      "MonthsWithHighSpendingOverLast6Months": 6,
      "MostRecentBillAmount": -0.24334867632207086,
      "MostRecentPaymentAmount": -0.36354131850988874,
      "TotalOverdueCounts": 1,
      "TotalMonthsOverdue": 12,
      "HasHistoryOfOverduePayments": 1,
      "y": true
   },
   "counterfactual_found": true,
   "counterfactual_plausible": true,
   "counterfactual_distance": 9.746452057288432e-05,
   "counterfactual_time": 30.357318878173828,
   "counterfactual_class": 0,
   "factual_class": 1,
   "valid_": true
}