{
   "found": true,
   "num_iterations": 19,
   "num_foil": 2,
   "_observation": [
      1.037255558551036,
      -0.1904201441565649,
      0.9024978924100217,
      0.3181305660829153,
      0.2731102875353145
   ],
   "_idx": 20,
   "factual_class": 1,
   "feature_bounds_splits": {
      "0": {
         "type": 1,
         "values": [
            null,
            1.0494170784950256
         ]
      },
      "1": {
         "type": 1,
         "values": [
            -0.18665774166584015,
            -0.17913293093442917
         ]
      },
      "2": {
         "type": 1,
         "values": [
            null,
            0.9016984105110168
         ]
      },
      "3": {
         "type": 1,
         "values": [
            null,
            0.32376915216445923
         ]
      },
      "4": {
         "type": 1,
         "values": [
            0.2650058716535568,
            0.27917709946632385
         ]
      }
   },
   "splits": [
      [
         2,
         0.9524651169776917,
         true
      ],
      [
         2,
         0.9411392211914062,
         true
      ],
      [
         2,
         0.9150896370410919,
         true
      ],
      [
         1,
         -0.20512772351503372,
         false
      ],
      [
         1,
         -0.2020493969321251,
         false
      ],
      [
         4,
         0.26238252222537994,
         false
      ],
      [
         1,
         -0.1945245862007141,
         false
      ],
      [
         4,
         0.27917709946632385,
         true
      ],
      [
         2,
         0.9016984105110168,
         true
      ],
      [
         3,
         0.32376915216445923,
         true
      ],
      [
         0,
         1.08590167760849,
         true
      ],
      [
         1,
         -0.18665774166584015,
         false
      ],
      [
         0,
         1.0494170784950256,
         true
      ],
      [
         1,
         -0.17913293093442917,
         true
      ],
      [
         4,
         0.2650058716535568,
         false
      ]
   ],
   "remaining_rules": [
      12,
      56,
      83,
      124,
      159,
      199,
      219,
      261,
      306,
      333
   ],
   "set_rules": [
      12,
      56,
      83,
      124,
      159,
      199,
      219,
      261,
      306,
      333
   ],
   "foil_estimated_class": [
      0
   ],
   "distance": 0.0002232487636535253,
   "extraction_time": 0.017260313034057617,
   "feature_bounds": {
      "0": {
         "type": 1,
         "values": [
            0.3951268121600151,
            1.0494170784950256
         ]
      },
      "1": {
         "type": 1,
         "values": [
            -0.18665774166584015,
            -0.17913293093442917
         ]
      },
      "2": {
         "type": 1,
         "values": [
            0.7356739640235901,
            0.9016984105110168
         ]
      },
      "3": {
         "type": 1,
         "values": [
            0.24818937480449677,
            0.32376915216445923
         ]
      },
      "4": {
         "type": 1,
         "values": [
            0.2650058716535568,
            0.27917709946632385
         ]
      }
   },
   "feature_bounds_compact": {
      "0": {
         "type": 1,
         "values": [
            0.1972992867231369,
            1.0494170784950256
         ]
      },
      "1": {
         "type": 1,
         "values": [
            -0.18665774166584015,
            -0.17913293093442917
         ]
      },
      "2": {
         "type": 1,
         "values": [
            0.7342748939990997,
            0.9016984105110168
         ]
      },
      "3": {
         "type": 1,
         "values": [
            0.24818937480449677,
            0.32376915216445923
         ]
      },
      "4": {
         "type": 1,
         "values": [
            0.2650058716535568,
            0.27917709946632385
         ]
      }
   },
   "feature_bounds_compact_count": {
      "0": {
         "type": 1,
         "values": [
            0.1972992867231369,
            1.0494170784950256
         ]
      },
      "1": {
         "type": 1,
         "values": [
            -0.18665774166584015,
            -0.17913293093442917
         ]
      },
      "2": {
         "type": 1,
         "values": [
            0.7342748939990997,
            0.9016984105110168
         ]
      },
      "3": {
         "type": 1,
         "values": [
            0.24818937480449677,
            0.32376915216445923
         ]
      },
      "4": {
         "type": 1,
         "values": [
            0.2650058716535568,
            0.27917709946632385
         ]
      }
   },
   "counterfactual_sample": [
      1.037255558551036,
      -0.18165774166584014,
      0.8966984105110168,
      0.3181305660829153,
      0.2731102875353145
   ],
   "counterfactual_distance": 0.0002191753226904046,
   "counterfactual_class": 0,
   "valid_": true
}