{
   "factual_sample": {
      "isMale": 1.0,
      "isMarried": 1.0,
      "AgeGroup": 2.0,
      "EducationLevel": 3.0,
      "MaxBillAmountOverLast6Months": -0.40475441127412737,
      "MaxPaymentAmountOverLast6Months": 0.2859216816269657,
      "MonthsWithZeroBalanceOverLast6Months": 1.0,
      "MonthsWithLowSpendingOverLast6Months": 1.0,
      "MonthsWithHighSpendingOverLast6Months": 5.0,
      "MostRecentBillAmount": -0.6984967528068727,
      "MostRecentPaymentAmount": 1.3930524973537173,
      "TotalOverdueCounts": 2.0,
      "TotalMonthsOverdue": 3.0,
      "HasHistoryOfOverduePayments": 1.0,
      "y": true
   },
   "counterfactual_sample": {
      "isMale": 1,
      "isMarried": 1,
      "AgeGroup": 2,
      "EducationLevel": 3,
      "MaxBillAmountOverLast6Months": -0.4151671677827835,
      "MaxPaymentAmountOverLast6Months": 0.26355385035276413,
      "MonthsWithZeroBalanceOverLast6Months": 1,
      "MonthsWithLowSpendingOverLast6Months": 1,
      "MonthsWithHighSpendingOverLast6Months": 5,
      "MostRecentBillAmount": -0.6937937745448708,
      "MostRecentPaymentAmount": 1.3905596531890239,
      "TotalOverdueCounts": 2,
      "TotalMonthsOverdue": 3,
      "HasHistoryOfOverduePayments": 1,
      "y": true
   },
   "counterfactual_found": true,
   "counterfactual_plausible": true,
   "counterfactual_distance": 0.0001509933782222195,
   "counterfactual_time": 45.686442375183105,
   "counterfactual_class": 1,
   "factual_class": 1,
   "valid_": false
}