{
   "counterfactual_sample": {
      "shucked_weight": 1.3861292792407034, 
      "diameter": 1.2306885417269942, 
      "whole_weight": 1.1925794190567407, 
      "shell_weight": 0.8382246482912458, 
      "viscera_weight": 1.0392812000143523, 
      "height": -0.050039, 
      "length": 0.8828213913692646, 
      "y": 0, 
      "sex": 2.0
   }, 
   "factual_class": 0, 
   "factual_sample": {
      "shucked_weight": 1.3861292792407034, 
      "diameter": 1.2306885417269942, 
      "whole_weight": 1.1925794190567407, 
      "shell_weight": 0.8382246482912458, 
      "viscera_weight": 1.0392812000143523, 
      "height": 0.8484424152684789, 
      "length": 0.8828213913692646, 
      "y": 0, 
      "sex": 2.0
   }, 
   "counterfactual_distance": 0.004156674137627455, 
   "counterfactual_class": 0, 
   "counterfactual_rule": {
      "shucked_weight": ">0.255175", 
      "viscera_weight": ">0.177064", 
      "height": "-0.107991< height <=-0.050039"
   }, 
   "counterfactual_time": 17.484129905700684, 
   "counterfactual_found": false
}