{
   "factual_sample": {
      "isMale": 1.0,
      "isMarried": 0.0,
      "AgeGroup": 2.0,
      "EducationLevel": 4.0,
      "MaxBillAmountOverLast6Months": 1.7236138237708067,
      "MaxPaymentAmountOverLast6Months": -0.18827627080347734,
      "MonthsWithZeroBalanceOverLast6Months": 0.0,
      "MonthsWithLowSpendingOverLast6Months": 0.0,
      "MonthsWithHighSpendingOverLast6Months": 6.0,
      "MostRecentBillAmount": 1.8122036846275351,
      "MostRecentPaymentAmount": -0.3747273409490208,
      "TotalOverdueCounts": 1.0,
      "TotalMonthsOverdue": 4.0,
      "HasHistoryOfOverduePayments": 1.0,
      "y": true
   },
   "counterfactual_sample": {
      "isMale": 1.0,
      "isMarried": 0.0,
      "AgeGroup": 2.0,
      "EducationLevel": 4.0,
      "MaxBillAmountOverLast6Months": 1.7236138237708067,
      "MaxPaymentAmountOverLast6Months": 0.27137247762862754,
      "MonthsWithZeroBalanceOverLast6Months": 0.0,
      "MonthsWithLowSpendingOverLast6Months": 0.0,
      "MonthsWithHighSpendingOverLast6Months": 6.0,
      "MostRecentBillAmount": 0.22890309390521651,
      "MostRecentPaymentAmount": -0.12118528013594593,
      "TotalOverdueCounts": 1.0,
      "TotalMonthsOverdue": 4.0,
      "HasHistoryOfOverduePayments": 1.0,
      "y": 0.0
   },
   "counterfactual_found": true,
   "counterfactual_plausible": true,
   "counterfactual_distance": 0.010741113782358603,
   "counterfactual_time": 8.5133695602417,
   "counterfactual_class": 0,
   "factual_class": 1,
   "valid_": true
}