{
   "factual_sample": {
      "pregnancies": 5.0,
      "glucose": 189.0,
      "blood_pressure": 64.0,
      "skin_thickness": 33.0,
      "insulin": 325.0,
      "bmi": -0.10059341751192273,
      "diabetes_pedigree_function": 0.3356067555749899,
      "age": 29.0,
      "y": false
   },
   "counterfactual_sample": {
      "pregnancies": 5.0,
      "glucose": 189.0,
      "blood_pressure": 64.0,
      "skin_thickness": 33.0,
      "insulin": 188.0,
      "bmi": -0.34642703104235617,
      "diabetes_pedigree_function": 0.3356067555749899,
      "age": 21.0,
      "y": 1.0
   },
   "counterfactual_found": true,
   "counterfactual_plausible": true,
   "counterfactual_distance": 0.04051727213760925,
   "counterfactual_time": 0.7901334762573242,
   "counterfactual_class": 1,
   "factual_class": 0,
   "valid_": true
}