{
   "counterfactual_sample": {
      "isMale": 1.0, 
      "EducationLevel": 3.0, 
      "MostRecentBillAmount": 1.405540937719145, 
      "MonthsWithLowSpendingOverLast6Months": 0.0, 
      "MaxPaymentAmountOverLast6Months": -0.250906, 
      "isMarried": 0.0, 
      "MaxBillAmountOverLast6Months": 1.2071409056777112, 
      "TotalOverdueCounts": 0.0, 
      "MonthsWithZeroBalanceOverLast6Months": 0.0, 
      "HasHistoryOfOverduePayments": 0.0, 
      "y": 1, 
      "TotalMonthsOverdue": 0.0, 
      "MostRecentPaymentAmount": 0.067218, 
      "AgeGroup": 2.0, 
      "MonthsWithHighSpendingOverLast6Months": 3.0
   }, 
   "factual_class": 1, 
   "factual_sample": {
      "isMale": 1.0, 
      "EducationLevel": 3.0, 
      "MostRecentBillAmount": 1.405540937719145, 
      "MaxPaymentAmountOverLast6Months": -0.2240647955152089, 
      "HasHistoryOfOverduePayments": 0.0, 
      "isMarried": 0.0, 
      "MaxBillAmountOverLast6Months": 1.2071409056777112, 
      "MostRecentPaymentAmount": 0.13350936256301646, 
      "y": 1, 
      "MonthsWithZeroBalanceOverLast6Months": 0.0, 
      "TotalMonthsOverdue": 0.0, 
      "TotalOverdueCounts": 0.0, 
      "MonthsWithLowSpendingOverLast6Months": 0.0, 
      "AgeGroup": 2.0, 
      "MonthsWithHighSpendingOverLast6Months": 3.0
   }, 
   "counterfactual_distance": 0.0002986711113667903, 
   "counterfactual_class": 1, 
   "counterfactual_rule": {
      "EducationLevel": "<=3.313755", 
      "MaxPaymentAmountOverLast6Months": "-0.349325< MaxPaymentAmountOverLast6Months <=-0.250906", 
      "MonthsWithLowSpendingOverLast6Months": "<=5.0", 
      "MostRecentPaymentAmount": "-0.330533< MostRecentPaymentAmount <=0.067218"
   }, 
   "counterfactual_time": 17.561450958251953, 
   "counterfactual_found": false
}