{
   "found": true,
   "num_iterations": 342,
   "num_foil": 156,
   "_observation": [
      0,
      1,
      0,
      0,
      0,
      1,
      0,
      10
   ],
   "_idx": 0,
   "factual_class": 0,
   "feature_bounds_splits": {
      "0": {
         "type": 2,
         "values": [
            null,
            null
         ]
      },
      "1": {
         "type": 2,
         "values": [
            null,
            0.5
         ]
      },
      "2": {
         "type": 2,
         "values": [
            null,
            null
         ]
      },
      "3": {
         "type": 2,
         "values": [
            null,
            null
         ]
      },
      "4": {
         "type": 2,
         "values": [
            null,
            0.5
         ]
      },
      "5": {
         "type": 2,
         "values": [
            null,
            null
         ]
      },
      "6": {
         "type": 2,
         "values": [
            0.5,
            1.5
         ]
      },
      "7": {
         "type": 2,
         "values": [
            null,
            7.5
         ]
      }
   },
   "splits": [
      [
         1,
         0.5,
         true
      ],
      [
         7,
         12.5,
         true
      ],
      [
         6,
         0.5,
         false
      ],
      [
         4,
         0.5,
         true
      ],
      [
         7,
         8.5,
         true
      ],
      [
         6,
         1.5,
         true
      ],
      [
         7,
         7.5,
         true
      ]
   ],
   "remaining_rules": [
      1,
      27,
      55,
      80,
      110,
      111,
      145,
      178,
      201,
      204,
      238,
      263,
      264,
      267
   ],
   "set_rules": [
      1,
      27,
      55,
      80,
      110,
      145,
      178,
      204,
      238,
      264
   ],
   "foil_estimated_class": [
      1
   ],
   "distance": 0.12083333333333332,
   "extraction_time": 0.007982254028320312,
   "feature_bounds": {
      "0": {
         "type": 2,
         "values": [
            null,
            0.5
         ]
      },
      "1": {
         "type": 2,
         "values": [
            null,
            0.5
         ]
      },
      "2": {
         "type": 2,
         "values": [
            null,
            0.5
         ]
      },
      "3": {
         "type": 2,
         "values": [
            null,
            0.5
         ]
      },
      "4": {
         "type": 2,
         "values": [
            null,
            0.5
         ]
      },
      "5": {
         "type": 2,
         "values": [
            null,
            1.5
         ]
      },
      "6": {
         "type": 2,
         "values": [
            0.5,
            1.5
         ]
      },
      "7": {
         "type": 2,
         "values": [
            null,
            7.5
         ]
      }
   },
   "feature_bounds_compact": {
      "0": {
         "type": 2,
         "values": [
            null,
            0.5
         ]
      },
      "1": {
         "type": 2,
         "values": [
            null,
            0.5
         ]
      },
      "2": {
         "type": 2,
         "values": [
            null,
            0.5
         ]
      },
      "3": {
         "type": 2,
         "values": [
            null,
            1.0
         ]
      },
      "4": {
         "type": 2,
         "values": [
            null,
            0.5
         ]
      },
      "5": {
         "type": 2,
         "values": [
            null,
            1.5
         ]
      },
      "6": {
         "type": 2,
         "values": [
            0.5,
            1.5
         ]
      },
      "7": {
         "type": 2,
         "values": [
            null,
            7.5
         ]
      }
   },
   "feature_bounds_compact_count": {
      "0": {
         "type": 2,
         "values": [
            null,
            0.5
         ]
      },
      "1": {
         "type": 2,
         "values": [
            null,
            0.5
         ]
      },
      "2": {
         "type": 2,
         "values": [
            null,
            0.5
         ]
      },
      "3": {
         "type": 2,
         "values": [
            null,
            1.0
         ]
      },
      "4": {
         "type": 2,
         "values": [
            null,
            0.5
         ]
      },
      "5": {
         "type": 2,
         "values": [
            null,
            1.5
         ]
      },
      "6": {
         "type": 2,
         "values": [
            0.5,
            1.5
         ]
      },
      "7": {
         "type": 2,
         "values": [
            null,
            7.5
         ]
      }
   },
   "counterfactual_sample": [
      0.0,
      0.0,
      0.0,
      0.0,
      0.0,
      1.0,
      1.0,
      7.0
   ],
   "counterfactual_distance": 0.12083333333333332,
   "counterfactual_class": 1,
   "valid_": true
}