{
   "factual_sample": {
      "Temperature": 1.2756215278694554,
      "Humidity": 2.3789602175026463,
      "Light": 1.014424487598945,
      "CO2": 2.2158833735740675,
      "HumidityRatio": 2.1456731490994803,
      "y": false
   },
   "counterfactual_sample": {
      "Temperature": -1,
      "Humidity": -1,
      "Light": -1,
      "CO2": -1,
      "HumidityRatio": -1,
      "y": 1.0
   },
   "counterfactual_found": false,
   "counterfactual_plausible": true,
   "counterfactual_distance": 1000,
   "counterfactual_time": 0.01247859001159668,
   "counterfactual_class": 1,
   "factual_class": -1,
   "valid_": false
}