{
   "factual_sample": {
      "variance_wti": -0.1938593581895316,
      "skewness_wti": -0.22467255930802746,
      "curtosis_wty": -0.41395243141912186,
      "entropy": 0.5392657845282003,
      "y": true
   },
   "counterfactual_sample": {
      "variance_wti": -0.019511895978625106,
      "skewness_wti": -0.22473688223991767,
      "curtosis_wty": -0.2789523953365043,
      "entropy": 0.5392014615963101,
      "y": true
   },
   "counterfactual_found": true,
   "counterfactual_plausible": true,
   "counterfactual_distance": 0.015202853183884927,
   "counterfactual_time": 2.2257416248321533,
   "counterfactual_class": 0,
   "factual_class": 1,
   "valid_": true
}