{
   "factual_sample": {
      "sex": 0.0,
      "length": 0.8411819763832166,
      "diameter": 0.676409429935641,
      "height": 0.4897799348943839,
      "whole_weight": 1.0294240974728193,
      "shucked_weight": 1.106769939326664,
      "viscera_weight": 0.9754132443803828,
      "shell_weight": 0.5759856404160256,
      "y": 0
   },
   "counterfactual_sample": {
      "sex": 0.0,
      "length": 0.8411819763832166,
      "diameter": 0.7267984400984913,
      "height": 1.4462132158919714,
      "whole_weight": 1.0090296822748293,
      "shucked_weight": 1.1180344288393271,
      "viscera_weight": 1.1396451302963055,
      "shell_weight": 0.8346323331148728,
      "y": 1
   },
   "counterfactual_found": true,
   "counterfactual_plausible": true,
   "counterfactual_distance": 0.013574846793336787,
   "counterfactual_time": 0.7644877433776855,
   "counterfactual_class": 1,
   "factual_class": 0,
   "valid_": true
}