{
   "counterfactual_sample": {
      "genergy": 11690, 
      "seismoacoustic": 0, 
      "ghazard": 0, 
      "shift": 1, 
      "energy": 0, 
      "maxenergy": 0, 
      "gdenergy": -48, 
      "gpuls": 235, 
      "nbumps4": 1.0, 
      "y": 0, 
      "nbumps5": 0, 
      "seismic": 0, 
      "nbumps": 0, 
      "gdpuls": 85.0, 
      "nbumps2": 0, 
      "nbumps3": 0
   }, 
   "factual_class": 0, 
   "factual_sample": {
      "genergy": 11690, 
      "maxenergy": 0, 
      "y": 0, 
      "shift": 1, 
      "energy": 0, 
      "seismoacoustic": 0, 
      "gdenergy": -48, 
      "gpuls": 235, 
      "nbumps4": 0, 
      "ghazard": 0, 
      "nbumps5": 0, 
      "seismic": 0, 
      "nbumps3": 0, 
      "gdpuls": -52, 
      "nbumps2": 0, 
      "nbumps": 0
   }, 
   "counterfactual_distance": 0.03200095170116583, 
   "counterfactual_class": 0, 
   "counterfactual_rule": {
      "nbumps4": ">0.228594", 
      "gdpuls": ">84.0"
   }, 
   "counterfactual_time": 18.64453101158142, 
   "counterfactual_found": false
}