{
   "factual_sample": {
      "isMale": 0.0,
      "isMarried": 1.0,
      "AgeGroup": 2.0,
      "EducationLevel": 2.0,
      "MaxBillAmountOverLast6Months": 2.7232388265316367,
      "MaxPaymentAmountOverLast6Months": 0.4738114363635562,
      "MonthsWithZeroBalanceOverLast6Months": 0.0,
      "MonthsWithLowSpendingOverLast6Months": 0.0,
      "MonthsWithHighSpendingOverLast6Months": 0.0,
      "MostRecentBillAmount": 2.7537163486654377,
      "MostRecentPaymentAmount": 1.8570947049081858,
      "TotalOverdueCounts": 1.0,
      "TotalMonthsOverdue": 2.0,
      "HasHistoryOfOverduePayments": 1.0
   },
   "counterfactual_sample": {
      "isMale": 0.0,
      "isMarried": 1.0,
      "AgeGroup": 2.0,
      "EducationLevel": 2.0,
      "MaxBillAmountOverLast6Months": 2.7232388265316367,
      "MaxPaymentAmountOverLast6Months": 0.4738114363635562,
      "MonthsWithZeroBalanceOverLast6Months": 0.0,
      "MonthsWithLowSpendingOverLast6Months": 0.0,
      "MonthsWithHighSpendingOverLast6Months": 0.0,
      "MostRecentBillAmount": 2.7537163486654377,
      "MostRecentPaymentAmount": 1.8570947049081858,
      "TotalOverdueCounts": 1.0,
      "TotalMonthsOverdue": 2.0,
      "HasHistoryOfOverduePayments": 1.0
   },
   "factual_class": 1,
   "counterfactual_class": 1,
   "counterfactual_found": false,
   "counterfactual_rule_id": 446,
   "counterfactual_rule": {
      "7": [
         null,
         0.5
      ],
      "11": [
         0.5,
         null
      ],
      "12": [
         1.5,
         2.5
      ],
      "6": [
         null,
         0.5
      ],
      "1": [
         0.5,
         null
      ],
      "9": [
         0.1524,
         null
      ]
   },
   "counterfactual_distance": 0.0,
   "counterfactual_time": 0.33629822731018066
}