{
   "counterfactual_sample": {
      "isMale": 1.0, 
      "EducationLevel": 4.0, 
      "MostRecentBillAmount": 0.5966356911513693, 
      "MonthsWithLowSpendingOverLast6Months": 0.0, 
      "MaxPaymentAmountOverLast6Months": -0.295641844938672, 
      "isMarried": 1.0, 
      "MaxBillAmountOverLast6Months": 0.4782476744979392, 
      "TotalOverdueCounts": 1.0, 
      "MonthsWithZeroBalanceOverLast6Months": 0.0, 
      "HasHistoryOfOverduePayments": 1.0, 
      "y": 0, 
      "TotalMonthsOverdue": 2.0, 
      "MostRecentPaymentAmount": -0.04326862126725737, 
      "AgeGroup": 3.0, 
      "MonthsWithHighSpendingOverLast6Months": 3.0
   }, 
   "factual_class": 0, 
   "factual_sample": {
      "isMale": 1.0, 
      "EducationLevel": 4.0, 
      "MostRecentBillAmount": 0.5966356911513693, 
      "MaxPaymentAmountOverLast6Months": -0.295641844938672, 
      "HasHistoryOfOverduePayments": 1.0, 
      "isMarried": 1.0, 
      "MaxBillAmountOverLast6Months": 0.4782476744979392, 
      "MostRecentPaymentAmount": -0.04326862126725737, 
      "y": 0, 
      "MonthsWithZeroBalanceOverLast6Months": 0.0, 
      "TotalMonthsOverdue": 2.0, 
      "TotalOverdueCounts": 1.0, 
      "MonthsWithLowSpendingOverLast6Months": 0.0, 
      "AgeGroup": 3.0, 
      "MonthsWithHighSpendingOverLast6Months": 3.0
   }, 
   "counterfactual_distance": 0.0, 
   "counterfactual_class": 0, 
   "counterfactual_rule": {
      "TotalOverdueCounts": ">0.450161", 
      "MaxPaymentAmountOverLast6Months": ">-0.376166", 
      "MostRecentBillAmount": ">-0.190168", 
      "MostRecentPaymentAmount": ">-0.308436"
   }, 
   "counterfactual_time": 19.15457797050476, 
   "counterfactual_found": false
}