{
   "counterfactual_sample": {
      "shucked_weight": -0.09853043852826254, 
      "diameter": 0.42446437912139023, 
      "whole_weight": -0.050460187260758384, 
      "shell_weight": -0.0634464609783469, 
      "viscera_weight": -0.36581382393298606, 
      "height": -0.2275450258538067, 
      "length": 0.217591, 
      "y": 0, 
      "sex": 1.0
   }, 
   "factual_class": 0, 
   "factual_sample": {
      "shucked_weight": -0.09853043852826254, 
      "diameter": 0.42446437912139023, 
      "whole_weight": -0.050460187260758384, 
      "shell_weight": -0.0634464609783469, 
      "viscera_weight": -0.36581382393298606, 
      "height": -0.2275450258538067, 
      "length": 0.2165907515924977, 
      "y": 0, 
      "sex": 1.0
   }, 
   "counterfactual_distance": 2.028857510393403e-05, 
   "counterfactual_class": 0, 
   "counterfactual_rule": {
      "shucked_weight": ">-0.109795", 
      "length": ">0.216591", 
      "shell_weight": "-0.09937< shell_weight <=0.062285"
   }, 
   "counterfactual_time": 17.887619018554688, 
   "counterfactual_found": false
}