{
   "counterfactual_sample": {
      "isMale": 0.0, 
      "EducationLevel": 4.0, 
      "MostRecentBillAmount": 1.6442342891653738, 
      "MonthsWithLowSpendingOverLast6Months": 0.0, 
      "MaxPaymentAmountOverLast6Months": -0.313536, 
      "isMarried": 1.0, 
      "MaxBillAmountOverLast6Months": 3.743689350183317, 
      "TotalOverdueCounts": 0.0, 
      "MonthsWithZeroBalanceOverLast6Months": 0.0, 
      "HasHistoryOfOverduePayments": 0.0, 
      "y": 1, 
      "TotalMonthsOverdue": 0.0, 
      "MostRecentPaymentAmount": 0.15560661054180067, 
      "AgeGroup": 2.0, 
      "MonthsWithHighSpendingOverLast6Months": 1.0
   }, 
   "factual_class": 1, 
   "factual_sample": {
      "isMale": 0.0, 
      "EducationLevel": 4.0, 
      "MostRecentBillAmount": 1.6442342891653738, 
      "MaxPaymentAmountOverLast6Months": -0.08985782784621557, 
      "HasHistoryOfOverduePayments": 0.0, 
      "isMarried": 1.0, 
      "MaxBillAmountOverLast6Months": 3.743689350183317, 
      "MostRecentPaymentAmount": 0.15560661054180067, 
      "y": 1, 
      "MonthsWithZeroBalanceOverLast6Months": 0.0, 
      "TotalMonthsOverdue": 0.0, 
      "TotalOverdueCounts": 0.0, 
      "MonthsWithLowSpendingOverLast6Months": 0.0, 
      "AgeGroup": 2.0, 
      "MonthsWithHighSpendingOverLast6Months": 1.0
   }, 
   "counterfactual_distance": 0.0005708802522821421, 
   "counterfactual_class": 1, 
   "counterfactual_rule": {
      "MaxPaymentAmountOverLast6Months": "<=-0.313536", 
      "MostRecentPaymentAmount": ">-0.197949", 
      "MaxBillAmountOverLast6Months": ">0.482413", 
      "MonthsWithHighSpendingOverLast6Months": ">0.059045"
   }, 
   "counterfactual_time": 19.392805099487305, 
   "counterfactual_found": false
}