{
   "factual_sample": {
      "sex": 1.0,
      "length": 0.4664272415087847,
      "diameter": 0.5252423994470907,
      "height": 0.011563294395590387,
      "whole_weight": 0.0015455714941164096,
      "shucked_weight": 0.14478253494525534,
      "viscera_weight": -0.1422759792140912,
      "shell_weight": -0.005969418156380771
   },
   "counterfactual_sample": {
      "sex": 1.0,
      "length": 0.4664272415087847,
      "diameter": 0.5252423994470907,
      "height": -0.11299000000000001,
      "whole_weight": -0.047299999999999995,
      "shucked_weight": 0.14478253494525534,
      "viscera_weight": -0.1422759792140912,
      "shell_weight": -0.005969418156380771
   },
   "factual_class": 0,
   "counterfactual_class": 1,
   "counterfactual_found": true,
   "counterfactual_rule_id": 681,
   "counterfactual_rule": {
      "4": [
         null,
         -0.0423
      ],
      "3": [
         null,
         -0.10799
      ],
      "0": [
         0.5,
         null
      ],
      "5": [
         -0.56826,
         null
      ],
      "1": [
         -0.13734,
         null
      ],
      "7": [
         -0.09218,
         null
      ]
   },
   "counterfactual_distance": 0.001636543066732652,
   "counterfactual_time": 0.7483870983123779
}