{
   "factual_sample": {
      "Temperature": -0.3005126366033534,
      "Humidity": 0.5422226586488175,
      "Light": -0.7724036570242273,
      "CO2": -0.1534598674713113,
      "HumidityRatio": 0.1719780103669807,
      "y": true
   },
   "counterfactual_sample": {
      "Temperature": -0.3005841398132882,
      "Humidity": 0.5421511554388827,
      "Light": 0.055858027177916096,
      "CO2": -0.17994411289691925,
      "HumidityRatio": 0.17190650715704595,
      "y": true
   },
   "counterfactual_found": true,
   "counterfactual_plausible": true,
   "counterfactual_distance": 0.026017680714323272,
   "counterfactual_time": 2.1212949752807617,
   "counterfactual_class": 0,
   "factual_class": 1,
   "valid_": true
}