{
   "factual_sample": {
      "Temperature": -0.5291493826842849,
      "Humidity": -0.1452712879612755,
      "Light": -0.7724036570242273,
      "CO2": -0.5985660556628911,
      "HumidityRatio": -0.3471822484332708,
      "y": true
   },
   "counterfactual_sample": {
      "Temperature": -0.5291493826842849,
      "Humidity": -0.1452712879612755,
      "Light": -0.03669655775314419,
      "CO2": -0.6117227375507355,
      "HumidityRatio": -0.34717076430834537,
      "y": true
   },
   "counterfactual_found": true,
   "counterfactual_plausible": true,
   "counterfactual_distance": 0.022478339883586336,
   "counterfactual_time": 1.8592092990875244,
   "counterfactual_class": 1,
   "factual_class": 1,
   "valid_": false
}