{
   "counterfactual_sample": {
      "isMale": 0.0, 
      "EducationLevel": 3.0, 
      "MostRecentBillAmount": -0.5747298298347541, 
      "MonthsWithLowSpendingOverLast6Months": 0.0, 
      "MaxPaymentAmountOverLast6Months": -0.376166025540068, 
      "isMarried": 0.0, 
      "MaxBillAmountOverLast6Months": -0.6213398285389738, 
      "TotalOverdueCounts": 1.0, 
      "MonthsWithZeroBalanceOverLast6Months": 0.0, 
      "HasHistoryOfOverduePayments": 1.0, 
      "y": 1, 
      "TotalMonthsOverdue": 8.0, 
      "MostRecentPaymentAmount": -0.2642411010550996, 
      "AgeGroup": 2.0, 
      "MonthsWithHighSpendingOverLast6Months": 0.0
   }, 
   "factual_class": 0, 
   "factual_sample": {
      "isMale": 0.0, 
      "EducationLevel": 3.0, 
      "MostRecentBillAmount": -0.5747298298347541, 
      "MaxPaymentAmountOverLast6Months": -0.376166025540068, 
      "HasHistoryOfOverduePayments": 1.0, 
      "isMarried": 0.0, 
      "MaxBillAmountOverLast6Months": -0.6213398285389738, 
      "MostRecentPaymentAmount": -0.2642411010550996, 
      "y": 0, 
      "MonthsWithZeroBalanceOverLast6Months": 0.0, 
      "TotalMonthsOverdue": 13.0, 
      "TotalOverdueCounts": 1.0, 
      "MonthsWithLowSpendingOverLast6Months": 0.0, 
      "AgeGroup": 2.0, 
      "MonthsWithHighSpendingOverLast6Months": 0.0
   }, 
   "counterfactual_distance": 0.00992063492063492, 
   "counterfactual_class": 1, 
   "counterfactual_rule": {
      "MostRecentBillAmount": "<=-0.517267", 
      "TotalMonthsOverdue": "<=8.0"
   }, 
   "counterfactual_time": 18.521224975585938, 
   "counterfactual_found": true
}