{
   "factual_sample": {
      "sex": 2.0,
      "length": -1.4489858478494209,
      "diameter": -1.4903180070669182,
      "height": -1.1839783068513945,
      "whole_weight": -1.286361748258961,
      "shucked_weight": -1.2925663268705263,
      "viscera_weight": -1.1367912883716234,
      "shell_weight": -1.2848336209451259,
      "y": true
   },
   "counterfactual_sample": {
      "sex": 2.0,
      "length": -1.6380514091786058,
      "diameter": -1.513886924207673,
      "height": -0.4997455031823085,
      "whole_weight": -0.8560481471028251,
      "shucked_weight": -1.2925663268705263,
      "viscera_weight": -1.1367912883716234,
      "shell_weight": -0.6071888523583338,
      "y": 0.0
   },
   "counterfactual_found": true,
   "counterfactual_plausible": true,
   "counterfactual_distance": 0.02858150008037724,
   "counterfactual_time": 0.446774959564209,
   "counterfactual_class": 0,
   "factual_class": 1,
   "valid_": true
}